{
  "configuratoreManager": {
    "listaConfiguratori": [
      {
        "username": "a",
        "password": "a"
      },
      {
        "username": "b",
        "password": "b"
      }
    ]
  },
  "fruitoreManager": {
    "listaFruitori": [
      {
        "username": "giorgio",
        "password": "bucella",
        "comprensiorio": {
          "nome": "Brescia",
          "comuni": []
        },
        "mail": "g.b@"
      }
    ]
  },
  "comprensorioManager": {
    "listaComprensori": [
      {
        "nome": "Brescia",
        "comuni": []
      }
    ]
  }
}